{
    "AFRO:ALGERIA": "DZA",
    "AFRO:ANGOLA": "AGO",
    "AFRO:BENIN": "BEN",
    "AFRO:BOTSWANA": "BWA",
    "AFRO:BURKINA_FASO": "BFA",
    "AFRO:BURUNDI": "BDI",
    "AFRO:CAMEROON": "CMR",
    "AFRO:CENTRAL_AFRICAN_REPUBLIC": "CAF",
    "AFRO:CHAD": "TCD",
    "AFRO:CONGO": "COG",
    "AFRO:COTE_DIVOIRE": "CIV",
    "AFRO:DEMOCRATIC_REPUBLIC_OF_THE_CONGO": "COD",
    "AFRO:EQUATORIAL_GUINEA": "GNQ",
    "AFRO:ERITREA": "ERI",
    "AFRO:ESWATINI": "SWZ",
    "AFRO:ETHIOPIA": "ETH",
    "AFRO:GABON": "GAB",
    "AFRO:GAMBIA": "GMB",
    "AFRO:GHANA": "GHA",
    "AFRO:GUINEA": "GIN",
    "AFRO:GUINEA_BISSAU": "GNB",
    "AFRO:KENYA": "KEN",
    "AFRO:LESOTHO": "LSO",
    "AFRO:LIBERIA": "LBR",
    "AFRO:MADAGASCAR": "MDG",
    "AFRO:MALAWI": "MWI",
    "AFRO:MALI": "MLI",
    "AFRO:MAURITANIA": "MRT",
    "AFRO:MOZAMBIQUE": "MOZ",
    "AFRO:NAMIBIA": "NAM",
    "AFRO:NIGER": "NER",
    "AFRO:NIGERIA": "NGA",
    "AFRO:RWANDA": "RWA",
    "AFRO:SENEGAL": "SEN",
    "AFRO:SIERRA_LEONE": "SLE",
    "AFRO:SOUTH_AFRICA": "ZAF",
    "AFRO:SOUTH_SUDAN": "SSD",
    "AFRO:TOGO": "TGO",
    "AFRO:UGANDA": "UGA",
    "AFRO:UNITED_REPUBLIC_OF_TANZANIA": "TZA",
    "AFRO:ZAMBIA": "ZMB",
    "AFRO:ZIMBABWE": "ZWE",
    "EMRO:DJIBOUTI": "DJI",
    "EMRO:EGYPT": "EGY",
    "EMRO:LIBYA": "LBY",
    "EMRO:MOROCCO": "MAR",
    "EMRO:SOMALIA": "SOM",
    "EMRO:SUDAN": "SDN",
    "EMRO:TUNISIA": "TUN"
}